rndua/__init__.py
rndua/browser.py
rndua/environment.py
rndua/format.py
rndua/rndua.py
rndua/data/android.tsv
rndua/data/chrome.csv
rndua/data/firefox.list
rndua-0.0.2.dist-info/LICENSE
rndua-0.0.2.dist-info/METADATA
rndua-0.0.2.dist-info/WHEEL
rndua-0.0.2.dist-info/top_level.txt
rndua-0.0.2.dist-info/RECORD
