Metadata-Version: 2.1
Name: rndua
Version: 0.0.2
Summary: A python module that generate random user agent based on rules
Home-page: https://github.com/xdavidwu/python-rndua
Author: xdavidwu
Author-email: xdavidwuph@gmail.com
License: UNKNOWN
Platform: UNKNOWN
Classifier: Programming Language :: Python :: 3
Classifier: License :: OSI Approved :: MIT License
Classifier: Operating System :: OS Independent
